AUTHORS.rst
CONTRIBUTING.rst
HISTORY.rst
LICENSE
MANIFEST.in
README.rst
setup.cfg
setup.py
docs/Makefile
docs/authors.rst
docs/conf.py
docs/contributing.rst
docs/history.rst
docs/index.rst
docs/installation.rst
docs/make.bat
docs/readme.rst
docs/usage.rst
miprimerproyectoexchange/__init__.py
miprimerproyectoexchange/cli.py
miprimerproyectoexchange/miprimerproyectoexchange.py
miprimerproyectoexchange.egg-info/PKG-INFO
miprimerproyectoexchange.egg-info/SOURCES.txt
miprimerproyectoexchange.egg-info/dependency_links.txt
miprimerproyectoexchange.egg-info/entry_points.txt
miprimerproyectoexchange.egg-info/not-zip-safe
miprimerproyectoexchange.egg-info/top_level.txt
tests/__init__.py
tests/test_miprimerproyectoexchange.py