Metadata-Version: 1.2
Name: miprimerproyectoexchange
Version: 0.1.0
Summary: Exchange lib example
Home-page: https://github.com/afernandocisneros/miprimerproyectoexchange
Author: Fernando Cisnero
Author-email: fer@gmail.com
License: GNU General Public License v3
Keywords: miprimerproyectoexchange
Platform: UNKNOWN
Classifier: Development Status :: 2 - Pre-Alpha
Classifier: Intended Audience :: Developers
Classifier: License :: OSI Approved :: GNU General Public License v3 (GPLv3)
Classifier: Natural Language :: English
Classifier: Programming Language :: Python :: 3
Classifier: Programming Language :: Python :: 3.5
Classifier: Programming Language :: Python :: 3.6
Classifier: Programming Language :: Python :: 3.7
Classifier: Programming Language :: Python :: 3.8
Requires-Python: >=3.5
